flake8_sorted_keys/__init__.py
flake8_sorted_keys/checker.py
flake8_sorted_keys-0.2.0.dist-info/DESCRIPTION.rst
flake8_sorted_keys-0.2.0.dist-info/METADATA
flake8_sorted_keys-0.2.0.dist-info/RECORD
flake8_sorted_keys-0.2.0.dist-info/WHEEL
flake8_sorted_keys-0.2.0.dist-info/entry_points.txt
flake8_sorted_keys-0.2.0.dist-info/metadata.json
flake8_sorted_keys-0.2.0.dist-info/top_level.txt
