Metadata-Version: 2.0
Name: flake8-sorted-keys
Version: 0.2.0
Summary: check keys are sorted in dict literals
Home-page: https://gitlab.com/yevhen-m/flake8-sorted-keys
Author: yevhen-m, eprykhodko
Author-email: UNKNOWN
License: MIT
Platform: UNKNOWN
Classifier: Framework :: Flake8
Classifier: Environment :: Console
Classifier: Intended Audience :: Developers
Classifier: License :: OSI Approved :: MIT License
Classifier: Programming Language :: Python
Classifier: Programming Language :: Python :: 2
Classifier: Programming Language :: Python :: 3
Classifier: Topic :: Software Development :: Libraries :: Python Modules
Classifier: Topic :: Software Development :: Quality Assurance
Requires-Dist: flake8 (>3.0.0)
